kvsparser/__init__.py
kvsparser/kvsparser.py
kvsparser-0.1.2.dist-info/LICENSE
kvsparser-0.1.2.dist-info/METADATA
kvsparser-0.1.2.dist-info/WHEEL
kvsparser-0.1.2.dist-info/top_level.txt
kvsparser-0.1.2.dist-info/RECORD
