Metadata-Version: 2.1
Name: kvsparser
Version: 0.1.2
Summary: Parsing AWS Kinesis Video Streams.
Home-page: https://github.com/rosealexander/kvsparser
Author: Alexander Rose
License: MIT-0
Platform: any
Classifier: Intended Audience :: Developers
Classifier: Natural Language :: English
Classifier: Development Status :: 5 - Production/Stable
Classifier: License :: OSI Approved :: MIT No Attribution License (MIT-0)
Classifier: Operating System :: OS Independent
Classifier: Programming Language :: Python
Classifier: Programming Language :: Python :: 3
Classifier: Programming Language :: Python :: 3.8
Classifier: Programming Language :: Python :: 3.9
Classifier: Programming Language :: Python :: 3.10
Classifier: Programming Language :: Python :: 3.11
Classifier: Programming Language :: Python :: 3.12
Classifier: Topic :: Scientific/Engineering
Classifier: Topic :: Scientific/Engineering :: Information Analysis
Classifier: Topic :: Utilities
Requires-Python: >=3.8
License-File: LICENSE
Requires-Dist: av
Requires-Dist: imageio
Requires-Dist: ebmlite
Requires-Dist: importlib-metadata ; python_version < "3.8"
